datasets_plus/__init__.py
datasets_plus/parsing.py
datasets_plus/utils.py
datasets_plus-0.1.0.dist-info/LICENSE
datasets_plus-0.1.0.dist-info/METADATA
datasets_plus-0.1.0.dist-info/WHEEL
datasets_plus-0.1.0.dist-info/top_level.txt
datasets_plus-0.1.0.dist-info/RECORD
