Metadata-Version: 2.1
Name: datasets-plus
Version: 0.1.0
Summary: A wrapper for HuggingFace datasets with additional utilities
Author-email: Maharshi Gor <mgor@cs.umd.edu>
License: MIT
Project-URL: Homepage, https://github.com/maharshi95/datasets-plus
Keywords: huggingface,datasets,wrapper,utilities
Classifier: Programming Language :: Python :: 3
Classifier: Programming Language :: Python :: 3.9
Classifier: Programming Language :: Python :: 3.10
Classifier: Programming Language :: Python :: 3.11
Classifier: License :: OSI Approved :: MIT License
Classifier: Operating System :: OS Independent
Classifier: Intended Audience :: Developers
Classifier: Intended Audience :: Science/Research
Classifier: Topic :: Scientific/Engineering :: Artificial Intelligence
Classifier: Topic :: Software Development :: Libraries :: Python Modules
Requires-Python: >=3.9
License-File: LICENSE
